honest/__init__.py
honest/honest.py
honest-0.2.1.dist-info/AUTHORS.rst
honest-0.2.1.dist-info/LICENSE
honest-0.2.1.dist-info/METADATA
honest-0.2.1.dist-info/WHEEL
honest-0.2.1.dist-info/top_level.txt
honest-0.2.1.dist-info/RECORD
