Metadata-Version: 2.1
Name: honest
Version: 0.2.1
Summary: ...
Home-page: https://github.com/MilaNLProc/honest
Author: Federico Bianchi
Author-email: f.bianchi@unibocconi.it
License: MIT license
Keywords: honest
Platform: UNKNOWN
Classifier: Development Status :: 2 - Pre-Alpha
Classifier: Intended Audience :: Developers
Classifier: License :: OSI Approved :: MIT License
Classifier: Natural Language :: English
Classifier: Programming Language :: Python :: 3
Classifier: Programming Language :: Python :: 3.6
Classifier: Programming Language :: Python :: 3.7
Classifier: Programming Language :: Python :: 3.8
Requires-Python: >=3.6
License-File: LICENSE
License-File: AUTHORS.rst
Requires-Dist: pandas
Requires-Dist: numpy
Requires-Dist: Unidecode (==1.3.2)
